{
  "title": "王凤仪性命哲学浅述",
  "subtitle": "完整修心路径（据以志编著 · 原书逐章展开）",
  "motto": "性是根，命是果。去习性，化禀性，圆满天性。",
  "parts": [
    {
      "id": "preface",
      "title": "前言与导论",
      "short": "前言",
      "chapters": [
        {
          "id": "全书路线图-心里有张地图",
          "title": "全书路线图（心里有张地图）",
          "content": "这本书分五篇，像五层台阶，一层一层往上走：\n\n| 篇目 | 核心 | 修什么 |\n|------|------|--------|\n| **第一篇 三界** | 性、心、身 | 认清自己从哪来、毛病在哪 |\n| **第二篇 五行** | 木火土金水 | 化禀性、拨阴反阳 |\n| **第三篇 四大界** | 志、意、心、身 | 从身界升到志界 |\n| **第四篇 性理疗病** | 认不是、找好处 | 病从性上来，也从性上解 |\n| **第五篇 崇俭结婚与胎教** | 婚姻、优生 | 重立人根，从家庭源头改命 |\n\n贯穿全书的纲领，先生用几句话就点透了：\n\n> **性是根，命是果。**  \n> **去习性，化禀性，圆满天性。**  \n> **道就是命，德就是性。**  \n> **道德就是性命的根源，哪一条道不会，哪种苦不能了。**\n\n记牢这四句，后面各篇都是往这四句里填血肉。\n\n---"
        },
        {
          "id": "前言-先认识这位-善人",
          "title": "前言：先认识这位「善人」",
          "content": "前言是以志先生写的，相当于给全书定调。我帮你提炼几条：\n\n**1. 凤仪先生是谁**\n\n辽宁朝阳山沟里的农夫，家贫未读书。因尽伦常、义赴友难，见性明道。预知旧世界（自私自利、贪得无厌的「创业世界」）将结束，大同世界将来，于是奔走呼号：「从此要换世界了！」\n\n**2. 他悟到了什么**\n\n父殁守芦墓，豁然贯通人生真义——什么是真苦、什么是真乐，苦怎么解、乐怎么得。立下宏愿：**翻转世界，重立人根。**\n\n**3. 他的学问从哪来**\n\n不是书本里搬来的，是**躬行实践中生出来的**。悔过而愈疮痨，才发明性理疗病；尽伦常而兴女学，才悟到家道是翻转世界的桥梁。\n\n**4. 全书三大体系**\n\n- **三界**（性、心、身）——主体  \n- **五行**——化气禀之偏  \n- **四大界**（志、意、心、身）——升境  \n\n三者不是并列三块，而是**互相贯通、有机整体**。目标：**死心化性、三界合一、五行攒簇、四大界达通。**\n\n**5. 五条日用口诀（极重要）**\n\n先生讲道常用这五条，你当日常功课记：\n\n1. **不争**\n2. **不贪**\n3. **不怨人**\n4. **找好处**\n5. **认不是**\n\n婆媳不和、夫妻反目、身心交病，往往就卡在这五条上。性理疗病的入门，也是这五条。\n\n**6. 读书态度**\n\n前言特别提醒：先生讲道**因时、因地、因人而异**，不能句句当普遍法则。例如嫡庶之道，时代变了便不适用。但精髓不变——**诚意、正心、修身、齐家**，对普通人来说，**修己不治人**。\n\n---"
        },
        {
          "id": "导论-性命-二字怎么解",
          "title": "导论：「性命」二字怎么解",
          "content": "导论是全书的理论地基，读不懂这里，后面三界五行都会浮。\n\n### 一、性命不是玄词，是日用\n\n**性**，是天性、品性、气质、性格。  \n**命**，凤仪先生给了新义——**命者名也**。\n\n人一生要当许多角色：儿女、夫妻、父母、同事、朋友……每个角色有个「名」，这个名就是命。有名就有应尽的责任，有责任就有应行的道。孝悌忠信，都从这儿生出来。\n\n> **性是根，命是果。扎下根，才能结果。**  \n> **人不照命（身份）去行，不但不能结果，连根也烂了。**\n\n所以「立命」不是算命改运，是**把当下这个角色尽圆满**——让人佩服，性中就放光；让人信服，命就增大。\n\n### 二、性与命，像灯罩与灯火\n\n> **命像灯火，性像灯罩。灯火加上罩，才能亮。**  \n> **人修命了，更得养性，才能灵。**\n\n性命必须同时修。先生突出「化性」之说，前人少讲至此。\n\n### 三、道德是性命的根源\n\n> **道就是命，德就是性。**  \n> **以命为主可立功，以性为主可立德。**  \n> **道德就是性命的根源，哪一条道不会，哪种苦不能了。**\n\n这不是离开伦理关系去空洞修性。完善伦理关系，是人的天职；古圣先贤千言万语，核心都在这儿。\n\n### 四、命可以改——性不好，才把命闹坏\n\n凤仪先生**反对命定论**。若命真改不了，修什么、善什么？\n\n> **人的命都是好命，只是性不好，才把命闹坏了。**  \n> **所以我教人去习性、化禀性。**\n\n人禀五行之气，有阴阳。阴气盛，天性被蔽；**拨阴取阳**，化禀性、圆满天性，五行顺转，连沉疴也可化。这是五行篇要细讲的。\n\n### 五、三命要分清楚\n\n先生把「命」分三层：\n\n| 三命 | 性质 | 态度 |\n|------|------|------|\n| **阴命** | 坏的 | 止之、消之 |\n| **宿命** | 假的（执著于算命、认命） | 不迷于此 |\n| **天命** | 真的 | 长之、用之 |\n\n尽伦立德，众人宾服，**天命增长**；不尽责、犯错误，众人不服，叫**丢命**。不必算命，命好坏在自己选择。\n\n### 六、性命双修，终点在志界\n\n性主内修（尽性、返本归真），命主外显（立功立德、济世利人）。**性离不开命，命离不开性。**\n\n性理为体，伦理为用。用功处：**死心化性**；归宿处：**志界**（四大界最高层）。志字，是全书的魂。\n\n---"
        }
      ]
    },
    {
      "id": "part1",
      "title": "第一篇 三界",
      "short": "三界",
      "chapters": [
        {
          "id": "第一篇-三界-第一章开篇",
          "title": "第一篇·三界：第一章开篇",
          "content": "好，前言和导论读完了，正式进入**第一篇 三界**。\n\n### 三界是什么\n\n> **天赋以性，地赋以命，父母生身——是谓三界。**  \n> **人非三界不能生。**\n\n| 三界 | 性质 | 对应 |\n|------|------|------|\n| **性** | 纯阳 | 德之根、天性、天理 |\n| **心** | 半阴半阳 | 命之根、道理 |\n| **身** | 纯阴 | 物之根、情理 |\n\n儒释道也可对应三界：儒从**立命**起，道从**炼身**起，佛从**养性**起——路不同，根在一处。\n\n与三界对应的还有**三理**（天理、道理、情理）和**三命**（天命、宿命、阴命），都在三界范畴内。\n\n### 第一章纲领：性分三层\n\n性要分三面看：\n\n1. **天性**——天所赋，纯阳无阴，大公无我，人人共有  \n2. **禀性**——气禀之偏，人间苦恼之源  \n3. **习性**——物欲所绕，禀性之根  \n\n修行次序：\n\n> **去习性 → 化禀性 → 圆满天性**\n\n习性不去，禀性绝不能化；禀性足，德性就亏；德性足，禀性就消。  \n前生的习性是今生的禀性，今生的习性是来生的禀性——所以**当下这一念一行，都在种因**。\n\n### 天性：真正的主人\n\n天性是三界中人的**真主人**。儒曰「天命之谓性」，佛曰「人人都有佛性」，老曰「道法自然」——说的都是它。\n\n天性是宇宙大生命与个体小我的统一，纯阳无阴，人我一体。以天性为主的人，能和世人和性，因为天性大公无私。\n\n---"
        },
        {
          "id": "第一章-性心身各论-续",
          "title": "第一章 性心身各论（续）",
          "content": "上回讲到「天性」，今天把「性、心、身」三块补全。\n\n### 一、禀性——动性，人间苦恼之源\n\n禀性就是常说的「脾气」「动性」。一发动，面红耳热、跳脚骂人、甚至动手；心里还夹着恨、怨、恼、怒、烦、嫉妒、虚荣、报复。\n\n**危害三条线：**\n- 伤己：内乱、生病\n- 伤人：家庭失和、夫妻反目\n- 伤世：社会不安\n\n对人用禀性，没有好结果，只会事与愿违。\n\n**禀性从哪来？**\n1. **遗传/先天**——禀性可遗传；胎教、教母比单纯母教更根本  \n2. **环境熏陶**——「染于苍则苍，染于黄则黄」  \n3. **宿世业因**——前生的习性是今生的禀性  \n\n**化解关键：** 争端初起，若一方真心说「**怨我呀**」，往往雾消云散。这不是软弱，是以天性应事。\n\n### 二、习性——禀性之根\n\n习性是后天染上的物欲、嗜好、坏习惯。**习性不去，禀性绝不能化。**\n\n习性为禀性之根；前生的习性是今生的禀性，今生的习性是来生的禀性——所以**当下每一念、每一行，都在种因**。\n\n### 三、人心——十四种毛病（要认、要戒）\n\n修心，就是化「人心」、长「道心」。人心一扩，贪财、贪位、贪权、贪享受，永无餍足，终至身败名裂。\n\n十四种人心，你当镜子照：\n\n| 人心 | 对治方向 |\n|------|----------|\n| 贪心 | 见利思义，唯义所在 |\n| 私心 | 公字当头 |\n| 妄心 | 认清现实，道心作主 |\n| 怨恨心 | **不怨人** |\n| 淫欲心 | 守伦常 |\n| 虚荣心 | 不求人赞 |\n| 嫉妒心 | 找好处 |\n| 牵缠心 | 放下 |\n| 多疑心 | 信人 |\n| 依赖心 | 自立 |\n| 挑剔心 | 容人 |\n| 争理心 | 认不是 |\n| 自满心 | 知不足 |\n| 执着心 | 不着物，着于道则神气生 |\n\n人心活动的根，是「**我**」占住灵魂。让道心作主，人心自退。\n\n### 四、道心——十六种功夫（要养、要长）\n\n人心惟危，道心惟微——道心在隐微处用功。\n\n十六项不必一次全做，选一两项深练即可：\n\n正见、尽伦、理解他人、责任心、适应心理、自我认识、爱心、公德心、宽容心、感恩心、平等心、诚信心、来应去静、常乐心、平常心、无心。\n\n**尽伦是道心最大体现：** 伦常不尽，谈不上自我解放。问题表面是人与人，实质是**心对心**。\n\n### 五、身——载道之具，勿著勿溺\n\n身是父母所生，是**载道之具**。尽伦立命、立功立德，都要通过身来完成。\n\n- 习性是人身堕落之源  \n- 身体健康来自心灵健康  \n- 身是受罪之物，勿活着溺爱、死后金玉殉葬  \n- **人身不过是借它来锻炼性命，使之会合**\n\n---"
        },
        {
          "id": "第二章-三理常存",
          "title": "第二章 三理常存",
          "content": "性、心、身是三界主体；**天理、道理、情理**是三界大用。\n\n> **性存天理，心存道理，身存情理。**\n\n### 天理（性上）\n与宇宙法则合一。恻隐、羞恶、是非、辞让等「闪光点」，培育实践，就是天命成长。\n\n### 道理（心上）\n不只会做人的道，还要会**物的道**——当车夫懂牲畜，当农人懂稼穑。  \n**真学道的，有一人学一人的道，才算真。**  \n不会当儿子、当丈夫，都是亏道。有道才有福，不明道有福也不会享。\n\n### 情理（身上）\n情是人之常情、情绪、感情，易表于外，故在身。  \n情理六法（知情、尽情、容情、圆情、顺情、忘情），核心：**刚柔相济**，该刚则刚，该柔则柔。\n\n**日用口诀：** 每一动作，思想是否合乎天理、人事、因果？能这样思想，就合道。\n\n---"
        },
        {
          "id": "第三章-三命消长",
          "title": "第三章 三命消长",
          "content": "三命如影随形，消长决定苦乐祸福。\n\n> **止宿命，了阴命，长天命。**\n\n| 三命 | 是什么 | 怎么办 |\n|------|--------|--------|\n| **天命** | 恻隐、羞恶、是非、辞让等光明面；尽伦立德、与人为善 | **长之** |\n| **宿命** | 钱、产、技能、知识等可见可触之物 | **止之**，以天命包宿命 |\n| **阴命** | 恨怨恼怒烦、贪争搅等阴暗面；伦常中的障碍、冤怨 | **了之** |\n\n**操作次第：**\n1. **立身**——学什么学好什么，干什么干好什么，让父母放心  \n2. **立命**——按名分尽责，让人佩服  \n3. **立德**——修心养性，与人为善，天命自长  \n\n**铁律：** 以天命包宿命，切勿使宿命包天命。只追富贵而忘修身齐家，家破人不远。\n\n---"
        },
        {
          "id": "第四章-三界分清",
          "title": "第四章 三界分清",
          "content": "先分清，再合一。分不清，谈合一都是空话。\n\n### 清三界的标准\n- **性清**——无脾气  \n- **心清**——无私欲  \n- **身清**——无嗜好  \n\n### 三界别连动\n- 心界有事，**不要连动性**  \n- 身界受伤，**不要动心**  \n\n### 失三宝\n- 一动性 → 失天道  \n- 一生气 → 失人道  \n- 一打人骂人 → 失身道  \n\n### 清三界的具体法\n| 负面 | 伤什么 | 对治 |\n|------|--------|------|\n| 怨人 | 身 | 不怨人 |\n| 包屈 | 气 | 不包屈 |\n| 后悔 | 性、命 | 不后悔 |\n| 贪 | 亏天理 | 戒贪 |\n| 争 | 亏人道 | 不争 |\n| 搅 | 亏因果 | 不搅 |\n\n**捷径：** 不责人而责己——得道的捷径，可惜人都不肯行。\n\n人只知身我，不知天上有个性我、地府有命我；**实有三身**。\n\n---"
        },
        {
          "id": "第五章-死心化性",
          "title": "第五章 死心化性",
          "content": "本篇用功核心，全在这一章。\n\n> **把贪心一去，当时就乐起来。**  \n> **想要化性，必得向后退。**  \n> **人非得把心死了不可。**\n\n世人不得道，只因怕人耻笑，总存个「好好」的心（贪好名、贪面子）。\n\n**化性三要：**\n1. **能欢喜，性就化**  \n2. **能忍受，性就清；能知足，心就了；能担事，身就了**  \n3. **不怨人三个字，妙到极点了**  \n\n天性向里归，禀性向外散。一尘不染，是一切不着住。\n\n**重要辨别：** 从不发脾气 ≠ 已化性。可能只是压住（含而未露）；内仍恼，仍是动禀性。**压火伤己，发火伤人，都是罪过。** 必先细心省察，认出自己的禀性，才能化。\n\n先生说：他能有今天，就因为「**性化透了**」。班上第一名，不是考第一，是**性化得最透**的。\n\n---"
        },
        {
          "id": "第六章-三界俱足",
          "title": "第六章 三界俱足",
          "content": "三界像高粱灌浆，**一点一点度**，急不得。\n\n> **三界俱足，自然合一。**\n\n**问：** 三宝怎能养足？  \n**答：** 必须把世界看破了才行。\n\n**天命是什么？** 就是名。省长有一省天命，一省人没好，要自责：「怨我呀！」——这叫**性能够笼住命**。心里不足，还是命不足。\n\n**伦常与因果：** 情就是因果。伦常之内，**尽**是道，**要**是恶。儿子当尽孝，不可要孝；丈夫当尽夫义，不可要求妻子如何如何。\n\n伦常中有难处、有人与你作对，说明那一处**德不足**，要从那里找道；道明白了，难关自过。\n\n---"
        },
        {
          "id": "第七章-三界合一",
          "title": "第七章 三界合一",
          "content": "> **三界要先分清，而后再合一。**\n\n「三人同心，其利断金」——这三人，是你内的**性（天人）、心（阴人）、身（世人）**。\n\n三界真合一，其力无穷。求道就是求合天道；不合天，终不合道。\n\n**不合的表现：**\n- 身做一事，心想别事——身心不合  \n- 遇逆事担不住——性心不合  \n\n**合一法门：**\n- 钻透一条道（如「不怨人」），才入阳气，三宝自足  \n- 格物 = 格除物欲，精化气、气化神  \n- 不怨人 → 正气 → 纯阳无阴  \n- 人是「器」：怨人则器破，不怨人则成完美之器；更高则「君子不器」，利益大众\n\n---"
        },
        {
          "id": "第八章-三界杂谈-七十条精要",
          "title": "第八章 三界杂谈（七十条精要）",
          "content": "这一章是语录集，因时因地而异，不可句句当普遍法则，但精义可提：\n\n1. **三世因果：** 性为前因，心为来因，身为现在  \n2. **不责人责己**——得道捷径（三岁孩儿都会怨人，学道要翻过来）  \n3. **顺俗失性，违俗成德**——张雅轩捐产兴女学，当时违俗，合天理  \n4. **止宿命如蝌蚪断尾**——产多尾大，难超凡；让产、捐产是止宿命实例  \n5. **现代是因果世界**——天道、人道、因果须同讲；不破因果，万难返天道  \n\n七十条不必一次读完，遇事儿来查一条，比通读更有用。\n\n---"
        },
        {
          "id": "第九章-结语",
          "title": "第九章 结语",
          "content": "> **人都求道，而不知道在平常；饮食起居都是道，可惜人都不察。**  \n> **翻世界要从细微处翻——翻个人心头一念。**  \n> **讲性即念佛教真经，讲命即念儒教真经，讲身即念道教真经。**  \n> **念书不如念人，念人不如念己。**\n\n儒释道三家，凤仪先生融在性心身、天理道理情理、立身立命立德里，不执教相，但在伦常中实修。\n\n---"
        },
        {
          "id": "第一篇总诀-三界修行路线图",
          "title": "第一篇总诀：三界修行路线图",
          "content": "给你一张可贴墙的总图：\n\n```\n认三界（性·心·身）\n    ↓\n存三理（天理·道理·情理）\n    ↓\n分三命（长天命·止宿命·了阴命）\n    ↓\n清三界（不怨·不包屈·不后悔·戒贪争搅）\n    ↓\n死心化性（认不是·找好处·不怨人·向后退）\n    ↓\n三界俱足（一点一点度，看破世界）\n    ↓\n三界合一（性心身一，纯阳无阴）\n```\n\n**日常五功课**（第一篇反复出现）：\n\n1. 遇事先**认不是**  \n2. 对人常**找好处**  \n3. 起怨时**不怨人**  \n4. 动性时**向后退**  \n5. 每事问：**合天理、合道理、合情理否？**\n\n---\n\n第一篇读到这里，「认清自己、分清三界、化性立命」的地基就算立住了。下一讲进入**第二篇 五行**——禀性分木火土金水，「认不是生真水、找好处生真金」等具体化性法门，那才是把第一篇的「化禀性」落到性格上。\n\n你这一遍读下来，哪一条最扎心？是「不怨人」，还是「止宿命」，或是「心界有事不要连动性」？想深聊哪条，下回可从那里展开。\n\n[REDACTED]"
        }
      ]
    },
    {
      "id": "part2",
      "title": "第二篇 五行",
      "short": "五行",
      "chapters": [
        {
          "id": "第二篇总纲-五行在三界",
          "title": "第二篇总纲：五行在三界",
          "content": "| 三界 | 五行对应 |\n|------|----------|\n| **性** | 仁义礼智信（五常） |\n| **心** | 五伦（兄弟、父母、祖等） |\n| **身** | 五情（喜怒悲恐惊） |\n\n**拨阴取阳**：把阴面（恨怨恼怒烦等）化掉，长阳面（仁义礼智信）。  \n**有真木才有真仁德，才能成道。**\n\n---"
        },
        {
          "id": "第一章-五行性理",
          "title": "第一章 五行性理",
          "content": "每种性分**阴阳两面**，形同而气质清浊随心变。\n\n### 木性（仁）\n\n| 阳木（真木） | 阴木 |\n|------------|------|\n| 仁德、能立、有主意、心口如一 | 不服人、硬顶、夸大、倔强 |\n| 忍辱、救世、顶天立地 | 头晕、麻木、中风、耳鸣、牙疼 |\n\n**阴木之根：不服人。**  \n**化法：** 化阴为阳，养仁德、爱物命；木是能立的。\n\n### 火性（礼）\n\n| 阳火（真火） | 阴火 |\n|------------|------|\n| 明理、领家、知进知退 | 争理、争功、贪、虚荣、外明内暗 |\n| 真刚 | 可与共患难，不可与共富贵；虎头蛇尾 |\n\n**阴火好恨。** 恨的表现：压怒、暗怨、伤自尊、越压越爆。  \n**伤身：** 心跳、失眠、神经紊乱。  \n**化法：** **一退就化**——打算化火性，知退即化；一味精进，火化不了。\n\n### 土性（信）\n\n| 阳土（真土） | 阴土 |\n|------------|------|\n| 信实、厚载、兜满家 | 怨人、不忠不信、耍滑 |\n| 真信：心口如一、雨打不进 | 多疑、反复 |\n\n**信分层次：** 信而不实 < 浅信 < 深信 < **真信**（阳土本质）。  \n李广射虎：信→情→力。\n\n### 金性（义）\n\n| 阳金（真金） | 阴金 |\n|------------|------|\n| 义气、分清、见义勇为、无我 | 分辨心、好挑刺、好叨咕、看人对看不见己错 |\n| 活泼、学人之长、即时改错 | 肺经病、胁肋痛、肝伤 |\n\n**化法：** 分辨心萌芽期就要**找好处**，成熟后难改。  \n**义的核心：无我**——弃小我成大家。\n\n### 水性（智）\n\n| 阳水（真水） | 阴水 |\n|------------|------|\n| 柔和、托天包地、不争、落底就下 | 愚鲁、好烦、退缩、邋遢、包屈 |\n| 水助万物生长 | 生回头气、优柔寡断、一生多受气 |\n\n**水能托地、包天，不争，只落底就下。**\n\n---"
        },
        {
          "id": "第二章-五行生克顺逆",
          "title": "第二章 五行生克顺逆",
          "content": "### 基本概念\n\n| 术语 | 含义 |\n|------|------|\n| **顺** | 按序前进（水生木木生火…） |\n| **克** | 横跳相克 |\n| **逆** | 倒序而行 |\n\n- **男五行：** 水木火土金（顺）  \n- **女五行：** 木水金土火（以逆为顺，与男错路）  \n- 时代变了，懂道独立的女性，也可与男同走顺路\n\n### 顺逆与境界\n\n| 状态 | 对应 |\n|------|------|\n| 能顺 | 神 |\n| 走逆 | 鬼 |\n| 走克 | 妖 |\n| 逆来顺受 | 仙 |\n| 克来让过 | 神 |\n| 五行攒簇合一 | 佛 |\n\n**不服人则心苦如被绑；能服人则松。**\n\n### 化克为生\n\n相克不能硬顶，要**拨阴取阳**，引入第三行：\n\n- 金克木 → 认不是、含垢纳污（阳水），或向土（宽厚）  \n- 水克火 → 立阳木（仁德），水生木、木生火  \n- 阴土 → **责己不怨人**，才能生阳金  \n\n**核心：** 只有阳面才能相生；阴木不能生阳火，阴水不能生木，须先化阴为阳。\n\n### 人生四季五行\n\n| 季节 | 五行 | 阶段 |\n|------|------|------|\n| 春 | 木 | 学道 |\n| 夏 | 火 | 行道 |\n| 秋 | 金 | 成道 |\n| 冬 | 水 | 了道 |\n\n土旺于四季。阴性走逆则苦；**正心持意**，阴可转阳。\n\n### 五行问性法\n\n性理疗病之一：病由五行**阴面**克逆或缺行所致，用**口念特定字音**，汰阴补阳。  \n（具体字音表在书中，此处知有此法门即可。）\n\n---"
        },
        {
          "id": "第三章-伦理五行",
          "title": "第三章 伦理五行",
          "content": "五行不只在个人，更在**家庭方位**。\n\n### 家庭五行方位\n\n| 方位 | 五行 | 职责 |\n|------|------|------|\n| 东 | 木 | 助满家 |\n| 南 | 火 | 明理、领满家 |\n| 中 | 土 | 主元气、兜满家 |\n| 西 | 金 | 圆情、提满家 |\n| 北 | 水 | 托满家 |\n\n### 角色定位（父母未入冬前）\n\n| 角色 | 位 |\n|------|-----|\n| 祖父 | 土 |\n| 父亲 | 火 |\n| 母亲 | 水 |\n| 长兄 | 木 |\n| 自己、姐妹、妯娌 | 金 |\n\n父母入冬（男60、女58）后，自己居**土位**，要**如如不动**；金位要**圆情**。\n\n### 家庭运用\n\n- 性是根，命是果；家不和，先**反求诸己**  \n- 本位各尽，五行圆转，家如机器般顺  \n- 阳气充盈则化险为夷；阴气密布则同境亦苦  \n\n### 社会五行\n\n士农工商官，各有其道：\n\n- **念书人**：不许怨人；书应变成人，不可书人两分  \n- **教师**：不可偏爱；观学生三命，教性教心，比父母更重  \n- **农人**：土位，产粮为世界，非为己多食  \n\n---"
        },
        {
          "id": "第四章-五行推转与相成",
          "title": "第四章 五行推转与相成",
          "content": "### 自身推转（拨阴取阳路径）\n\n以女为例（男理同，序不同）：\n\n```\n阴水 → 温柔慈祥 → 阳金（义）\n阳金 → 找好处、认因果 → 阳土（信）\n阳土 → 开阔诚厚 → 阳火（礼）\n阳火 → 戒贪、让、恕 → 阳木（仁）\n```\n\n### 人我之间：化克为生（藏性法）\n\n对方来克，不硬顶，**移位**：\n\n| 你 | 对方克 | 你藏到 |\n|----|--------|--------|\n| 火 | 水 | 土 |\n| 土 | 木 | 金 |\n| 金 | 火 | 水 |\n| 水 | 土 | 木 |\n| 木 | 金 | 火 |\n\n### 伦理推转案例：朱耀庭\n\n祖父居土位，悟到「我不会当老掌柜」，向家人悔改，买糖给孙辈，改行兴女学、行善。  \n**土变 → 金生水 → 水生木 → 木生火 → 火生土**，全家精神面貌连锁好转。\n\n**关键：** 五行能否推转，**关键还在我**——自转了，对方自然相生。\n\n### 推转 vs 圆转\n\n- **推转**：按序向前（男木火土金水，女木水金土火）  \n- **圆转**：逆了也能转——拨阴取阳，阳面无克无逆  \n- 运用时**知先知后**，先明对面心性，应机变化  \n\n---"
        },
        {
          "id": "第五章-真五行浅说-全书最实用",
          "title": "第五章 真五行浅说（全书最实用）",
          "content": "这是第二篇的**核心法门**——五条功夫，生五种真五行：\n\n| 功夫 | 生 | 作用 |\n|------|-----|------|\n| **认不是** | 真水 | 闭地狱门、明心丹、无穷之力 |\n| **找好处** | 真金 | 开天堂路、暖心丸、聚万灵 |\n| **认因果** | 真土 | 消怨气、厚德载物 |\n| **达天时** | 真火 | 明时势、因时施教 |\n| **达全体** | 真木 | 顾大局、仁德立 |\n\n### 认不是（生真水）\n\n- 以非为是、认贼作父，是万恶之根  \n- 人不认不是，怨结不解；真心认不是，怨如烟雾散  \n- 性理疗病钥匙：不是→是，迷→觉  \n- 凤仪先生青年悔过愈疮痨，即此  \n\n### 找好处（生真金）\n\n- 不找好处，夫妻反目、婆媳不和、父子相怨  \n- 救命之恩一例：虽后责骂，念前恩不恼，即生真金  \n- **存他人好处越多，阳气越足**  \n- 进阶：**反面找好处**——从反面也能找出好处，是更深功夫  \n\n### 认因果（生真土）\n\n- 一切有因必有果；认因果，怨气自消  \n- 以诚相待，太和阳气如日照雪，**消因果**  \n- 「地势坤，君子以厚德载物」  \n- 动念即因；**君子慎其独**  \n\n### 达天时（生真火）\n\n- 不明性而强求，如叫鸟潜水、鱼飞天，是**无明**  \n- 好心想改变人，若带禀性（恨铁不成钢），以力服人，非心服  \n- 农事春播夏锄秋收冬藏，**人生各阶段各有其时**  \n- 达时才能理解、管理、教育人  \n\n### 达全体（生真木）\n\n- 顾全大局，不执一端  \n- 与「真木」之仁德、能立相应  \n\n---"
        },
        {
          "id": "第六章-五行杂谈-精要摘录",
          "title": "第六章 五行杂谈（精要摘录）",
          "content": "七十条语录，举其纲领：\n\n1. 人为五行所成，五伦如五脏，缺一不可活  \n2. 五伦不圆、不尽本位，五行不转，阴气阻塞  \n3. **人的命都是好命，只是性不好，才把命闹坏了**  \n4. 性来归命——性格要配角色；儿媳当温柔圆活而不失原则  \n5. 阴火女入富家，如火投水，终被灭；水克火，能欺夫至死  \n6. **找好处万阵俱破，认不是百难全消**  \n\n---"
        },
        {
          "id": "第七章-结语",
          "title": "第七章 结语",
          "content": "第二篇归结五句话：\n\n> **性界：仁义礼智信**  \n> **心界：五伦**  \n> **身界：五情**  \n> **社会：士农工商官**  \n\n> **顺五行是人道，超克逆是神仙，五行攒簇是佛。**  \n\n> **命都是好命，只因性不好，才把命闹坏了。**\n\n---"
        },
        {
          "id": "第二篇修行路线图",
          "title": "第二篇修行路线图",
          "content": "```\n① 认自己主行（木火土金水）及阴阳\n        ↓\n② 识阴面表现（恨怨恼怒烦、不服、争理…）\n        ↓\n③ 拨阴取阳（先化本行，再谈相生）\n        ↓\n④ 五真功夫：认不是·找好处·认因果·达天时·达全体\n        ↓\n⑤ 家庭/社会本位各尽 → 五行圆转\n        ↓\n⑥ 人我相遇 → 藏性化克为生\n```\n\n**日常只练两条，足够：**\n\n- Morning：**找好处**（先从身边人找一条）  \n- Evening：**认不是**（今天哪一处不是，写下来）\n\n---\n\n第二篇读毕，你已有一套**识性、化性、用性**的完整工具。下一讲进**第三篇 四大界**——从身界、心界、意界升到**志界**，那是「死心化性」之后的升境之路。\n\n你若有兴趣，可先对照自己：木火土金水哪一行偏？阴面哪一条最常犯？下回可从你的主行细讲化法。\n\n[REDACTED]"
        }
      ]
    },
    {
      "id": "part3",
      "title": "第三篇 四大界",
      "short": "四界",
      "chapters": [
        {
          "id": "四大界总图",
          "title": "四大界总图",
          "content": "| 界 | 对应 | 一句话 |\n|----|------|--------|\n| **志界** | 佛国 | 事坏人不坏，如如不动 |\n| **意界** | 天堂 | 常乐，能容能包，但阳中有阴 |\n| **心界** | 苦海 | 常思常贪，患得患失 |\n| **身界** | 地狱 | 败事、败家、损公 |\n\n**学道效率：**\n- 用心学 → 学一得一  \n- 用意学 → 学一得三  \n- 用志学 → 学一得万  \n\n今人拿心学佛，离佛界亿万里。\n\n---"
        },
        {
          "id": "第一章-四大界各论",
          "title": "第一章 四大界各论",
          "content": "### 一、以什么「当人」\n\n| 用事 | 评价 |\n|------|------|\n| **以身行事** | 坏的 |\n| **以心行事** | 假的，不那么信人 |\n| **以意行事** | 好的，但仅能自身好，不能化人 |\n| **以志行事** | 真的，自己成且能化人；志到哪里，真到哪里 |\n\n**事坏人不坏的，就是志界人。** 孔子困于陈蔡仍坦荡，耶稣钉十字架仍用志——五教圣人无不以志当人。\n\n### 二、志界（最高）\n\n- 纯阳无阴（就性理言），与宇宙大生命合一  \n- 事坏人不坏：事业败了，人不败；常人事业一败就颓  \n- 真到志界，一丝气火都没有，只有**真乐**（性天之乐，不随外境变）  \n- 生死看透：死是另一种生的开始  \n- 无争、内省不疚；认因果则逆来顺受  \n- 不争名如入火不焚，不贪财如入水不溺  \n- **伦常不尽，到不了志界**；须尽伦立命、死心化性，三界合一升华而来  \n\n### 三、意界（次高）\n\n- **大义宽宏**，能容能化；净心——不容他人之不对、阴气不入  \n- 如皮球：针尖大孔，气就漏；**意要严密**  \n- 颜回箪瓢陋巷不改其乐——乐的是道，不是贫  \n- 阳中有阴：享天福，福尽仍可能轮回；**不到志界，出不了轮回**  \n- 相当于罗汉级  \n\n### 四、心界（多数人在此）\n\n- 私利第一，享受第一，贪多无厌，勾心斗角  \n- **强加于人的「好心」**：要人按己意办，不成则怨恨——「恨铁不成钢」常是此  \n- **贪高必糟糕**：高处人争，久必落；真高人常在低处  \n- 多思多虑：无事有事，有事无事  \n- **半好人**：能容不能化——外面忍，内里存阴，久则成病  \n- **欲速则不达**：学道是「为道日损」，去习气化禀性；**努劲是一时冲动，立志才是持久**  \n- 学道和求学问不同：求学问日有所增，学道日有所损  \n\n### 五、身界（最低）\n\n- 私心恼怒恨怨萃心 → 阴气充塞 → 成疾  \n- 心界苦海 → 堕入身界地狱  \n- 不能成事，只能败事；心界人聚财，身界人破败  \n- 家庭败家子，社会蠹虫；如失灵车闸，走地狱路  \n\n---"
        },
        {
          "id": "第二章-四大界定位",
          "title": "第二章 四大界定位",
          "content": "### 定在哪一界\n\n| 定位 | 归宿 |\n|------|------|\n| **定在志界** | 跳出三界，了生脱死 |\n| **定在意界** | 神界，享人间福报或天福，福尽仍轮回 |\n| **在心界** | 无边苦海 |\n| **在身界** | 地狱 |\n\n**两种定位：**\n1. **终身定位**——这一生要到哪里  \n2. **随时定位**——眼前这件事，用哪一界处理（小事不忽视，为最终归宿积资粮）\n\n### 关键语录\n\n- 定在志界：贫富得失荣辱丧亡一切不顾，**如如不动**，只知以志当人  \n- **志要时时知足，才能定住**；人只知求大求高，绝不能定志  \n- 占便宜乐的、吃亏生气的，都不是好人；**必到志上，才能无动无不动**  \n- 私用公款善款留给儿孙，等于给儿孙喝毒药  \n- 凤仪先生：「始而定意，真灵了；还嫌小，才定志——不挣钱也不花钱，只……」\n\n---"
        },
        {
          "id": "第三章-四大界分清",
          "title": "第三章 四大界分清",
          "content": "> **能分清四大界，一切道、一切事，就都会了。**\n\n### 核心原则\n\n- 无事时常思：志界人、意界人，性心身各什么样？  \n- **哪一界人来，用哪一界待他**  \n- **志能化，意能包，心能分，身能败**  \n- 人在道中寻道所以难寻——如人在屋里欲求全屋形状，不可得；**必得四大界分清**\n\n### 自检：你在哪一界？\n\n| 检验 | 志界 | 意界 | 心界 | 身界 |\n|------|------|------|------|------|\n| 对人 | 感恩 | 感义 | 感感情 | 感冤 |\n| 公私 | 无他人无我 | 为公忘私 | 占便宜乐 | 损人为己 |\n| 着色眼镜 | — | — | 戴黄镜见皆黄 | — |\n\n**坦山背女过河**：坦山放下了，小和尚还背着——坦山无心，在志意界；小和尚心界「好人」，心里仍存女像。\n\n**心界好人**：外面好，内里动；读很多书、很文气，一辈子仍在心界。\n\n---"
        },
        {
          "id": "第四章-四大界活用-本篇核心",
          "title": "第四章 四大界活用（本篇核心）",
          "content": "### 总诀\n\n> **志意心身，须要活用。**  \n> **遇高人要比他高不点，遇矮人要比他矮不点。**\n\n| 用法 | 效果 |\n|------|------|\n| 用志 | 越遇逆境越乐；不做德自有德，不修福自有福 |\n| 用意 | 意气要多大有多大 |\n| 用心 | 心理能千变万化 |\n| 用身 | 绝不能累着 |\n\n### 一、诚意\n\n- 诚在意界：不动气火  \n- 真诚其意：专一、不分  \n- **诚意即净心**——外境生死苦乐不动  \n- **诚意：一点也不怨人，一点不存人**\n\n### 二、立志\n\n- 志是灵魂的统帅、精神的灯塔  \n- 不立志，逆境无方向；**立起志来，精神立可振起**  \n- 立志不为功名富贵，为升境、成完人、止于至善  \n- 处顺境不被迷惑，处逆境不被吓倒  \n\n### 三、定志\n\n- **定才能灵**——天道四时不错，因有定  \n- 志界人：穷不变志，富不动心；人赞更谦，人毁外平内坚  \n- 不争理、所过者化、无说、和天合一  \n- **志诚：试以成败观之**——得意忘形、潦倒变节，皆非志诚  \n\n### 四、夺志（接命法）\n\n- 如果树**接码条**：把古圣今贤的志接在自己身上  \n- 凤仪先生：青年夺叔叔之孝志；35岁义赴友难，夺羊角哀之志而大悟  \n- 接古人之命，性中即有古人灵光，virtue 仍存，能相助今日  \n\n### 五、用志与用意\n\n> **禀性化了就是意；翻转世界，小事用意，大事用志。**  \n> **用志一划万代罪孽皆消。**\n\n- 遇考（魔考）须**定住**——一动就是地狱种  \n- 用心：好挑理、好计较，过则伤人  \n- 用意：宽宏大量，过了也不伤和气  \n- **志诚则动**：孟子「志诚则动」  \n\n### 六、挪界与落界\n\n**上升路：** 身 → 心 → 意 → 志（须逐级升）  \n\n**堕落路（极快）：**\n- 志界一丢志 → **直落身界（地狱）**  \n- 意界一滑 → **落心界（苦海）**  \n\n志界人不顾小节人情；**志一丢，如大厦忽倒**，极可怕。\n\n### 七、四大界结合三界\n\n- 志=佛国，意=天堂，心=苦海，身=地狱  \n- 志意心身是**道根**  \n- 消脾气了因果，了贪心出苦海，了意念到志界（佛国）  \n- **修道**=自知、自净、自丰、自全（道全德备）  \n\n---"
        },
        {
          "id": "第五章-四大界达通",
          "title": "第五章 四大界达通",
          "content": "- **性是本，志是根**——志如天雨，无心地滋润万物  \n- 须志意心身**达通**，才能普度众生  \n- 大人以天下人为一家；到极点，三千大千世界皆与我为一  \n- **成佛从底下向上托**——像挖井向深，不往高挖；上下达通、四大界合一即佛  \n- 志属水：托地包天，不动不不动；**上善若水，志几于道**  \n- 道是让的，心是载道的，身是圆情的  \n\n---"
        },
        {
          "id": "第六章-四大界杂谈-精要",
          "title": "第六章 四大界杂谈（精要）",
          "content": "1. **什么是圣、什么是佛？** 尽人合天。圣佛是人做的；神佛是天性之异名，天性本空  \n2. **尽人**=人道圆满；**合天**=与含容万有的天合一  \n3. 洗净污垢 → 天性复明 → 归根返本 → 超凡入圣  \n4. 各教路径不同，归宿一也  \n\n---"
        },
        {
          "id": "第七章-结语",
          "title": "第七章 结语",
          "content": "> **我原先的命在因果世界，一点一点取回来，现在我的命在佛国了。**  \n> **定才能灵。**  \n> **道只是一条道，佛神人物都从一条道来——只是道的火候难掐。**  \n> **身行不圆满 → 心不足 → 意不出 → 志也不出。**  \n> **八德就是八门，无论从哪一门，都可走进佛国。**\n\n---"
        },
        {
          "id": "第三篇修行路线图",
          "title": "第三篇修行路线图",
          "content": "```\n分清自己在哪一界（身/心/意/志）\n        ↓\n终身定位（志界）+ 随时定位（此事用哪界）\n        ↓\n诚意（不怨人、不存人）→ 立志 → 定志\n        ↓\n夺志（接圣贤之志）+ 活用（遇高略高、遇矮略矮）\n        ↓\n大事用志、小事用意；不用心学、不用身行\n        ↓\n防落界（志丢直落地狱，意滑落苦海）\n        ↓\n四大界达通 → 尽人合天 → 佛国\n```\n\n**三条日常功课：**\n\n1. **晨起问**：今天这事，我准备用哪一界？  \n2. **遇事问**：我现在是在用心，还是在用志？  \n3. **睡前检**：今天有没有「半好人」——外面忍、里面存阴？\n\n---\n\n第三篇读到这里，三界、五行、四大界的理论框架就齐了。下一讲进**第四篇 性理疗病**——认不是、找好处、挖根源、笑能愈病、哭能愈病，把前面化性落到**治病**上。\n\n你若有感触：常在心界「好心」强加于人，还是已在用志？可下回从此细讲。\n\n[REDACTED]"
        }
      ]
    },
    {
      "id": "part4",
      "title": "第四篇 性理疗病",
      "short": "化病",
      "chapters": [
        {
          "id": "第四篇总图",
          "title": "第四篇总图",
          "content": "```\n病因链：看人不对（心病）→ 动脾气（性病）→ 身病\n         ↓\n治法链：认不是 → 找好处 → 悔过道过 → 挖根源 → 化性 → 拨阴取阳（笑/哭）\n         ↓\n根本：化性养神，神足病自消（不只靠药力）\n```\n\n| 概念 | 含义 |\n|------|------|\n| **性** | 气禀性——恨怨恼怒烦五毒 |\n| **理** | 五行性理、伦理关系 |\n| **心病** | 专好寻思人家不对、有贪心 |\n| **性病** | 性中常动脾气 |\n| **身病** | 心病必至于性病，性病必至于身病 |\n\n**能反过来，病就好了。** 所以教人：去习性、化禀性、圆满天性。\n\n---"
        },
        {
          "id": "第一章-性理疗病法的来源",
          "title": "第一章 性理疗病法的来源",
          "content": "### 凤仪先生自己的愈病\n\n守芦墓时听杨柏讲善书，豁然：\n\n> **「古圣争罪，今愚争理。」**\n\n当场跪在院里，指名骂自己：\n\n> **「就打着人家不对，你生气算你对怎的！」**\n\n又哭又笑——哭的是世人还在迷，笑的是找到了路。**次日疮痨全愈。**\n\n### 总原则（开篇四则）\n\n1. **劝病以道德为本**——病是什么？就是**过**；把过道出来，病就好了  \n2. **病吃气、疮吃火**——不生气不上火，饿死病疮  \n3. **心病→性病→身病**——看人不对应是心病，动脾气是性病，身跟着病  \n4. **看人不对应，正是你不对**——真明白这个，病自消  \n\n### 后来怎么传开的\n\n守父墓时劝病者日多；办女义学、奔走东北华北，四十年风里尘里，性理疗病从实践长成完整理论体系。西医学心身医学兴起时，凤仪先生已实践半个多世纪。\n\n---"
        },
        {
          "id": "第二章-性理疗病法的原理与准则",
          "title": "第二章 性理疗病法的原理与准则",
          "content": "### 一、病因原理\n\n**不动气禀性，不得病**（传染病、外伤、一般感冒除外）。\n\n| 类型 | 是什么 | 怎么来的 |\n|------|--------|----------|\n| **气禀性** | 恨怨恼怒烦 | 人事不遂、伦常受伤 |\n| **习性** | 贪图享受、自私 | 越贪越怨，与禀性恶性循环 |\n\n**阴气过盛是致病主因**——事不遂心、人不对应便**动性**；阴气经伦理关系积累，终成身病。\n\n### 二、五毒与五脏\n\n凤仪先生总结：\n\n> **怒伤肝，恨伤心，怨伤脾，恼伤肺，烦伤肾。**\n\n| 阴五行 | 易动 | 伤 |\n|--------|------|-----|\n| 阴木 | 怒 | 肝 |\n| 阴火 | 恨 | 心 |\n| 阴土 | 怨 | 脾 |\n| 阴金 | 恼 | 肺 |\n| 阴水 | 烦 | 肾 |\n\n### 三、生气与病的关系\n\n- **寒病越生气越寒**——气属阴，重浊下凝，易患腰腿痛  \n- **疮症越生气毒火越大**——等于给毒火添油  \n- 生气、上火，正是**给疾病上肥料**  \n- **猫食碗子招苍蝇**——内里有阴，才引外患  \n\n### 四、心身医学印证\n\n- 怒时幽门括约肌痉挛 → 胃痛呕吐  \n- 抑郁 → 胃蠕动减弱、胃酸异常 → 溃疡  \n- 消化系统是心理的**晴雨表**  \n- 「火奶」：母亲生气，婴儿吃母乳腹泻——从母亲心性找根源  \n- 消极情绪削弱免疫；一瞬间暴怒，后果须长时间才能治愈  \n\n### 五、除四不正，万病皆消\n\n**忿懥、恐惧、好乐、忧患**——四不正全除，万病皆消。\n\n### 六、性理疗病五准则\n\n1. **明确**：某种气禀性（五行阴面）→ 某种病  \n2. **化性**：变化致病的气禀性  \n3. **悔过、道过**：亮出思想，解开疙瘩  \n4. **挖根源**：因人、因事、因财致病的思想根  \n5. **笑或哭**：拨阴取阳  \n\n### 七、六条方法（加转移注意力）\n\n6. **转移注意力**——扭转致病的思想焦点  \n\n**关键提醒：**\n- 化性、悔过、道过——**必须真心实意**，否则无效  \n- 劝病者须**品德高尚、有威信**，**绝不收谢礼**  \n- 病人若鄙视劝病者，法再灵也不灵  \n- 可配合**问性法**（见五行篇）  \n\n### 八、劝病不难\n\n见着姑娘，就问她姑娘怎么当、性质啥样；她愿说就让她尽量说，说完了还问，**慢慢自然就过来了，自然就好了**。\n\n---"
        },
        {
          "id": "第三章-典型病例-按治法分类",
          "title": "第三章 典型病例（按治法分类）",
          "content": "这一章是**案例集**，按方法分组，每则都可当教材。\n\n### 一、悔过、道过愈病\n\n| 病例 | 要点 |\n|------|------|\n| **赵家孙媳气臌** | 阴土性，嫌家贫夫愚，闷气不说 → 大肚子；翻过来：祖母侍候时感恩，口说「我有罪了，累及祖母」 |\n| **王恕忱转食症** | 三界有过则病：性动五毒→天灾，心私邪念→地灾，身犯伦常→人灾；向父母磕头认罪，吐沫水两盆，病愈 |\n| **刘玉成瘫痪** | 善辩争理，阴火太盛 → 瘫；躺枕上，家人来一个磕一个，向母说「我不会当儿子」、向弟说「我不会当弟弟」……**第三日能走八里** |\n| **宫占一宿疾** | 十二年胃病，木克土，长期闷气、专看人不对 → 翻过来认不是，气放出来，病愈 |\n| **张星南** | 被小侍者顶撞，自打嘴巴，窝气火 → 孙若愚说破「你自己打自己嘴巴那桩事」，当众道过而愈 |\n\n**火瘫与寒瘫**：刘玉成是气火瘫——认不是、找好处，立愈。\n\n### 二、挖根源愈病\n\n| 病例 | 要点 |\n|------|------|\n| **儿媳病** | 凤仪先生骑驴回家一百多里，一路只想病根；到家问清：与妯娌争产、心中不平 → 说破，立愈 |\n| **冯铭坤肿瘤** | 医院要手术，她逃回；查病因：邻居欠钱不还、打官司判不公 → 认「争理不对」，不药而愈 |\n| **马淑风疮症** | 专回忆，忽想起对外甥媳妇冤枉不满 → 颠倒一下：我若处她境地也会这样想 → 豁然开朗 |\n| **朱循天劝祁春生** | 挖病源——找长期存心、因人因病的那一桩 |\n\n**王朴厚转食症**：为一碟榨菜被后母误解，心中窝气不说 → 说破后大哭大吐，三月积滞尽出，立愈。\n\n### 三、化性愈病\n\n| 病例 | 要点 |\n|------|------|\n| **赵品三七年瘫痪** | 明心见性：明心=知各类人之道，见性=知自己禀性什么色、什么味、多大劲；木土水性，一动黑气升起；抓牢「小鬼」（禀性），黑气从腰眼蒸出，**霍然而愈** |\n| **刘玉清** | 木克土，板滞、看人不对、暗气暗憋 → 见人**先开口说话**，木生火、火生土，打开封闭心境 |\n\n**赵品三要诀**：知禀性什么色、什么味、发动时多大劲；外界一触动，见阴气升起，化除即愈。\n\n### 四、转移注意力愈病\n\n**高佐臣**：三年神经衰弱、七个月几乎没睡，数百付药无效。张雅轩：义学饭专能治病；引到后菜园劳动，**跟着走、注意力转移** → 食欲增、能睡；再让倒出心里恨怨谁 → 「看家人不对把人气病了，这是你最大的不对」→ 当众道过十余日，痊愈。\n\n### 五、笑能愈病\n\n> **病怕乐，一乐就好；邪崇也怕乐。**\n\n- **徐老母心口疼**： rigid、有怨气、耳聋不能听道 → 李子和学老太太和颜悦色，徐老母大笑两小时，**阴气从胃排出**，心口疼愈  \n- **某小姐**：李子和劝病（接续病例）  \n- **某抑郁少女**：阴木阴水，Li 坐转椅忽然大转喊救命 → 她大笑，「精神监狱开了缝」；教她**多看好处、少看不对**——不对生气是阴，好处痛快是阳  \n\n**法拉第**：头痛看喜剧，不药而愈——「小丑进城，胜过十个医生。」\n\n### 六、哭能愈病\n\n憋屈时，**该哭就得哭**——哭完心里敞亮，郁结阴气排出。别拦人哭；哭是健康保险阀。\n\n> **神出鬼没**——乐是神，阴气是鬼；神出鬼没，万病立消。\n\n---"
        },
        {
          "id": "第四章-性理疗病机理初探",
          "title": "第四章 性理疗病机理初探",
          "content": "### 一、心与病\n\n> **心是主要机关。** 生疮人心里生气，气变火，疮越发重；有病人生气，气变晦气，病越发重。\n\n### 二、达与不通\n\n- **上达意圆，下达情圆**——今人不达，事不从心则神伤、心塞，两界都病，身界怎能不病  \n- 动时若能**觉**，就是能达  \n- 读圣贤书知圣贤心志，也叫达  \n\n### 三、气色辨病\n\n| 气色 | 含义 |\n|------|------|\n| **新鲜** | 天灾——性界或天理有亏 |\n| **黑暗** | 疾病——心界或伦常有亏 |\n\n### 四、性理疗病与伦理疗病统一\n\n> **恨怨恼怒烦是致病根本因素。** 病从这条渠道进来，也必从这条渠道回去。\n\n- 家庭：夫妻吵、父子责善、婆媳不和、兄弟争讼  \n- 社会：权势名利倾轧、患得患失  \n- 惯常心理：「怨他，不怨我」「他气我，我才生气」——**我生气有理**  \n- 康德：因他人无理而生气，是**为他人的过失惩罚自己**  \n\n### 五、家庭信息相通\n\n- 老人属**阳气**，儿女属**阴气**  \n- **骂老人=截断阳气** → 大肚子病（表嫂案例）  \n- 根干叶：祖先父母与子孙信息相通；**积善余庆，积不善余殃**  \n- 夫妻不和如水搅混 → 儿女如鱼，易病  \n- 葱叶吹气两头捏住一拍打就破——气憋久了必爆  \n\n### 六、用药与化性\n\n> **病像贼，药像兵，身体像民户。** 兵大杀尽贼，固然了祸；若只把贼撵走，兵不能常给民户看家，贼回来祸更大。\n\n- 医生只知药力，不知境遇和心性  \n- **主张化性养神——神足则病自然好**  \n\n### 七、认不是与找好处\n\n- 专好看人家不对而生气 → **正是你不对**；真明白，病自消  \n- 不会当人是过：不会当父母、不会当儿女……都是过  \n- 气禀性深，怨人则动性生阴，**不健康的精神，哪能有健康的身体**  \n- 先生说：「人说道好不得好，心里尽存人不对，怎能得好？」  \n\n### 八、用意与意念\n\n- **病是寒的，意不敢去；疮属火，意还不敢离开**——越摸越注意，疮越重  \n- **多思则肾中精气不归根** → 必病  \n- 固意地乐 → 真乐出 → 阴气如烟消，万病立消  \n\n---"
        },
        {
          "id": "第五章-结语",
          "title": "第五章 结语",
          "content": "1. **肾如阴阳鱼**，属水藏神；意念住此，心肾自交  \n2. **钱维三问**：「别的病好了，肚里病块怎么不好？」  \n   先生：「**谁管它好不好，你好了，它也就好了。**」——病长在人身上，心性转了病自好；只盯病忘了人，病根难除  \n3. **不能自立，不能自定**——被人惹生气是寒，被事引得高兴是火  \n\n---"
        },
        {
          "id": "性理疗病实操手册",
          "title": "性理疗病实操手册",
          "content": "### 第一步：认病从哪来\n\n问自己三句：\n1. 我最近**恨怨恼怒烦**哪个常动？  \n2. 我对谁**看不对、存不对**？  \n3. 我有没有**闷气不说**、**争理不认不是**？  \n\n### 第二步：找根源\n\n静坐回忆——因**人、因事、因财**，哪一桩心里过不去？  \n像马淑风、冯铭坤那样，一宗一宗想，直到「豁然开朗」。\n\n### 第三步：翻过来\n\n| 旧习惯 | 新做法 |\n|--------|--------|\n| 看人不对 | **认不是**——看家人不对把人气病了，这是我最大的不对 |\n| 存人不对 | **找好处**——多看好处是阳，多看不对是阴 |\n| 闷气不说 | **道过**——当众或向当事人说出，解开疙瘩 |\n| 专盯病 | **化性养神**——你好了，病就好了 |\n\n### 第四步：拨阴取阳\n\n- 能笑则笑——病怕乐  \n- 该哭则哭——憋屈哭出来，阴气排出  \n- 转移注意力——别老想病，去劳动、去帮人  \n\n### 第五步：配合伦常\n\n- 向该道歉的人**道歉**（刘玉成向全家磕头）  \n- 向该感恩的人**感恩**（赵家孙媳向祖母）  \n- **伦常理顺，拨阴反阳，病自愈**——常见  \n\n---"
        },
        {
          "id": "本篇与前三篇的衔接",
          "title": "本篇与前三篇的衔接",
          "content": "| 前三篇 | 第四篇 |\n|--------|--------|\n| 三界分清 | 心病、性病、身病一条链 |\n| 五行化性 | 哪种阴性能→哪种病 |\n| 四大界 | 用心治病效低，用志化性效高 |\n| 不争不怨、认不是找好处 | **直接当药方** |\n\n凤仪先生一辈子劝病，不收钱、不图名，凭的就是**人道**——病是过，过在**因他人无理而生气**；把过道出来，性化了，神足了，病还有什么站得住脚？\n\n---\n\n第四篇到这里。下一讲进**第五篇 崇俭结婚与胎教**——从家庭源头**重立人根**，婚姻怎么选、怎么处、怎么优生。\n\n你若此刻有具体的不舒服或心里过不去的桩事，也可照这五步试——**先找根源，再认不是**；不必等读完五篇才动手。\n\n[REDACTED]"
        }
      ]
    },
    {
      "id": "part5",
      "title": "第五篇 崇俭结婚与胎教",
      "short": "家道",
      "chapters": [
        {
          "id": "第五篇总图",
          "title": "第五篇总图",
          "content": "```\n女子义学（教母）→ 崇俭结婚（断双头蛇）→ 夫妇正位（天清地宁）\n        ↓\n根本教 + 胎教 + 婴儿教 + 儿童教\n        ↓\n下一代质量 ← 婚姻质量 ← 父母心性\n```\n\n| 概念 | 含义 |\n|------|------|\n| **崇俭结婚** | 无彩礼、无嫁妆，男女自立，以道德相尚 |\n| **储金立业** | 解决「财血」问题，节制生活、全力为公 |\n| **根本教** | 夫妇婚前婚后必修的性理伦理 |\n| **教母** | 先教母亲做人，再谈母教 |\n| **生成** | 父母当时什么心性，孩子生出来就什么禀性 |\n\n**核心比喻：**\n\n> 你（包括丈夫）包的饺子是什么馅，你自己还不知道吗？何用问别人。\n\n---"
        },
        {
          "id": "第一章-从女子义学到崇俭结婚",
          "title": "第一章 从女子义学到崇俭结婚",
          "content": "### 一、为什么从妇女起\n\n- 世界由**否卦**转**泰卦**，妇女是转折关键 → **姑娘是世界的源头**\n- 1906年起，在锦州、朝阳一带办**女子义学**\n- 研究妇德女道，倡**崇俭结婚**、**储金立业**\n\n### 二、批判旧俗：双头蛇\n\n长春一带嫁女，娘家拿很多嫁妆，婆家还要重彩礼——像**双头蛇**：\n- 娘家贪、婆家也贪\n- 债还多年，搅扰两家\n- 官员、商人也为妻儿女倾家荡产、损公肥私\n- 只顾小家庭，**扔掉老人**——良心丧尽\n\n**崇俭结婚**：无嫁妆、无彩礼，男女**自立**，以道德相尚，同甘共苦——**斩断双头蛇**。\n\n### 三、新家庭什么样\n\n- 不依赖、不管束、以道德相尚\n- 婚前须学**夫妇相处之道**、婆家伦理\n- 须懂**刚正之道**（丈夫）、**媳妇之道**（妻子）\n\n### 四、崇俭结婚的形式\n\n| 做法 | 说明 |\n|------|------|\n| **自愿结合** | 不限财产、门第、相貌、文凭，重德业 |\n| **集体婚礼** | 1937年沈阳十对新人集体崇俭结婚 |\n| **娶女婿** | 无儿老人，女婿入赘、孩子随母姓——尽孝续宗 |\n| **尽义务不挣钱** | 陶复生听「天底下有一件出贵的事没人干」→ 到义学尽义务；后与官宦小姐王景新崇俭结婚，相敬如宾，二子皆出色 |\n\n**案例**：王淑英嫁赤贫李连喜——邻村新娘哭她，她说崇俭结婚带来男女平等、各自独立、互不管束；后来二子大学毕业，于国有用。\n\n### 五、推倒旧三从\n\n> 古代「三从」极无道理——父亲把女儿卖妓馆，女儿也从吗？\n\n要**推倒旧三从，让女子读书自立**。\n\n---"
        },
        {
          "id": "第二章-婚姻质量决定下一代质量",
          "title": "第二章 婚姻质量决定下一代质量",
          "content": "### 一、四种婚姻（对应四大界）\n\n| 婚姻层次 | 夫妻状态 | 对孩子 |\n|----------|----------|--------|\n| **志界** | 感恩、无说、恩德、不怨人；男子领、女子助 | 至乐 |\n| **意界** | 感义 | 较好 |\n| **心界** | 感感情、有礼义、开始相管 | 一般 |\n| **身界** | 感冤、打骂、为财产衣物 | 糟 |\n\n**生成律**：生孩子时，父母心性、行为什么样，孩子禀性、行为就什么样。父母先善后恶、先恶后善，孩子往往跟着走。\n\n### 二、宿命婚姻 vs 理想婚姻\n\n**以宿命为主的婚姻**（钱、地位、权势、外貌）= **买卖婚姻**：\n- 生活内容就两字：**收入、支出**\n- 外貌、财产一失，感情立散\n- 婚前装好、婚后露馅——**以阴命为主的婚姻**\n\n**理想婚姻**：\n> **结婚是为了世界，生儿育女也是为了世界。**\n\n责任对自己、对配偶、对老人、对后代——荡涤买卖婚姻的污泥浊水。\n\n### 三、彩礼之害\n\n- 千年彩礼绳索，**妇女是最大受害者**\n- 把女儿当投资、卖女儿——「泼出门的水」\n- 彩礼换不来纯爱，反成控制、侮辱\n\n### 四、婚姻不是两个半圆合成整圆\n\n- 夫妻性格**永不会完全一样**——刚柔相济、长短互补\n- **强求一致，差异反而扩大**；过度亲密，反而疏远——「淡中滋味长」\n- 不能「存异」、强加己意 → 误会苦恼\n- **能会对付人人之道（对方心性变化的规律），叫作达彼岸**\n\n**优生不单靠生物因素**——性理学说研究心性阴阳消长，才是完整答案。\n\n---"
        },
        {
          "id": "第三章-智力与个性的先天因素",
          "title": "第三章 智力与个性的先天因素",
          "content": "### 一、核心观点\n\n- **子女就是父母的一通活碑**\n- **夫为天，妻为地；天清地宁，生孩赛如神童**\n- 先天（遗传）是内因、物质基础；后天（环境教育）是外因——**缺一不可**\n- 巴甫洛夫：「婴儿出生三天后再教育，已经迟了三天。」\n\n### 二、遗传与婚姻\n\n- 近亲结婚之害——山区换亲、白痴代代相传的案例\n- 古人知「男女同姓，其生不蕃」\n\n### 三、案例印证（父母孕期 → 子女禀性）\n\n| 案例 | 孕期状态 | 子女特点 |\n|------|----------|----------|\n| 朱氏三女 | 长女：新媳妇受压，敢怒不敢言 | 倔强、好争、记仇 |\n| | 次女：家庭受 Restricted，母亲 depressed | 柔顺、逆来顺受 |\n| | 三女：环境转顺 | 独立、有主见、有威望 |\n| 王氏子 | 山区苦役、环境 primitive，但心地善良、听 folk songs | 胆大、少笑、极聪明 |\n\n**说明**：不是「怀孕吃啥补啥」那么简单——**母亲（及家庭）整个心性环境，就是孩子的「馅」**。\n\n---"
        },
        {
          "id": "第四章-胎教与优生",
          "title": "第四章 胎教与优生",
          "content": "### 一、教母先于母教\n\n> **讲母教，不如先讲教母。**\n\n- 孩子真假（禀性善恶），**查母亲便知**\n- 尽孝悌的子女从**德**上来；败产的从**孽**上来\n\n### 二、丈夫的责任（极重要）\n\n凤仪先生把**丈夫打骂妻子**列为**四大恶风**之一：\n\n| 行为 | 母亲心里 | 泄到哪里 |\n|------|----------|----------|\n| **骂女人** | 恼气（显威风，不敢还口） | 胎儿 |\n| **打女人** | 恨气（杀气，不敢还手） | 胎儿 |\n\n女人不能把气撒在男人身上，**最后泄到子女身上**——直接伤胎元，**罪极大**。\n\n> 人不治天治，人不治地治——违背伦常，天地以病治之。\n\n### 三、孕妇怎么做\n\n**性界**：去习性、化禀性（五毒）、复天性  \n**心界**：去私心存道心——孝悌慈、尽本分、为公  \n**身界**：健康、勤劳，由性天、道心统领  \n\n**三界合一** = 胎教根本。\n\n**具体：**\n- 衣着洁净、环境整洁\n- 心情如春风和煦——**不动气禀性，不忧不恐**\n- 丈夫**诚心协力**，绝不骂打\n- 配合**五行性理**拨阴取阳\n\n### 四、现代科学印证\n\n- 母亲情绪 → 血液生化物质 → 经胎盘影响胎儿\n- 母亲压抑、 irritable → 胎动频率、强度可增加数倍\n- 长期 negative mood → 影响发育，甚至先天缺陷\n- 日本「英才制造工程」：127名孕妇，体操、音乐、阅读、保持愉快——效果随孩子成长而显\n\n### 五、教育四环（不可缺一）\n\n```\n根本教 → 胎教 → 婴儿教 → 后天教育\n```\n\n崇俭结婚者，婚前婚后须学此四环；寒暑农闲办讲习班，深化性理伦理。\n\n---"
        },
        {
          "id": "第五章-崇俭结婚-新村-胎教-重立人根",
          "title": "第五章 崇俭结婚—新村—胎教—重立人根",
          "content": "### 一、夫妇正位\n\n> **现在的夫妇，男管女、女管男，互相搅扰，便是地狱家庭。**  \n> **我倡男女不相管束，男刚女柔各正本位，就是要化地狱为天堂。**\n\n| 角色 | 要求 |\n|------|------|\n| **男子** | 如天清；立三刚——性刚、心刚、身刚 |\n| **女子** | 如地宁；性从天理、心从道理、身从情理 |\n\n**三刚倒：**\n- 发脾气 → 性刚倒\n- 有私欲、吹毛求疵 → 心刚倒\n- 打人骂人、有嗜好 → 身刚倒\n\n**刚** = 刚正、爽朗、不卑不亢——**绝非刚暴、大男子主义**  \n**柔** = 柔和、文静、有韧性——**绝非软弱**\n\n- 丈夫**领妻不管妻**，妻子**助夫不累夫**\n- 男要心正，女要意诚\n- 只守自己的道——前妻不孝敬老人，**不恨不念**，你仍尽孝，才算守住男子道\n\n### 二、储金立业与气血论\n\n> **人是天地间的气，钱财是天地间的血。气血周流，哪能不好！**\n\n| 问题 | 解法 |\n|------|------|\n| **人（气）** | 崇俭结婚 → 提高下一代质量，遏贪享、损公 |\n| **财（血）** | 储金立业 → 生活需要有所节制，全力为公 |\n\n> **不明此二事，不能治世。**\n\n**婚姻质量 → 家庭质量 → 下一代质量**——重立人根的逻辑链。\n\n### 三、新村实验（1942亮中河畔）\n\n**约法三章：**\n1. **不动性**（不准发脾气）——性界\n2. **生产归公**——心界\n3. **遵守公约**——身界\n\n公约由村民共同研究制定；1942–1948十对崇俭结婚夫妇在此实践，追访子女长达五六十年——以志先生称为**重大社会科学实验**。\n\n### 四、男刚女柔的边界\n\n- **只适用于家庭伦理**，不用于职场（女校长、女教员都是强者）\n- 刚 = 有主见、刚正；柔 = 贤内助、贤母\n- **能成就大事的男人，哪位没有贤内助？英雄哲士，哪位不是贤母所生？**\n- 夫妻如戏——都争主角，戏唱不下去；**刚柔相济，对立统一，方为至美**\n\n---"
        },
        {
          "id": "全书总结-第五篇末-总结论",
          "title": "全书总结（第五篇末·总结论）",
          "content": "以志先生归结凤仪学说：\n\n- **性命之学**（三界·五行·四大界）是**主体**\n- **家庭伦理**是**重点**\n- 二者纵横交错，成完整体系\n- 崇俭结婚与胎教，是**重立人根**的关键环节\n\n凤仪先生：**文盲、放牛、扛活**——学问全从**实践**来。  \n**命者名也**——立命就是尽好本分、尽全职责。  \n**诚意、正心、修身、齐家**——功夫全在诚意正心；家齐则国治。\n\n**行不真，还是出不了数。** 化禀性、去习性、复天性——志=佛国，意=天堂，心=苦海，身=地狱，都不出本身。\n\n---"
        },
        {
          "id": "第五篇实操手册",
          "title": "第五篇实操手册",
          "content": "### 未婚 / 择偶\n\n1. 重**德业**，轻门第财产相貌  \n2. 问：这段关系是志界、意界、心界还是身界？  \n3. 能否**存异**、刚柔互补，而非改造对方？  \n\n### 婚前\n\n1. 学**根本教**：夫妇道、婆家伦理、五行性理  \n2. 若行崇俭结婚：双方自立，无彩礼嫁妆，不搅两家  \n\n### 孕期（胎教）\n\n1. **天清地宁**——丈夫不骂不打，妻子不动五毒  \n2. 环境整洁，心情和煦  \n3. 每日检：今天有没有恼气、恨气要泄到孩子身上？  \n\n### 育儿\n\n1. **根本教 → 胎教 → 婴儿教 → 儿童教**——一环不可缺  \n2. 夫妻不和如水搅混——**先齐家，再谈其他**  \n3. 看孩子禀性，先**查父母当时的心性**  \n\n---"
        },
        {
          "id": "五篇全书闭环",
          "title": "五篇全书闭环",
          "content": "| 篇 | 修什么 | 第五篇怎么用 |\n|----|--------|--------------|\n| 三界 | 性心身分清 | 胎教要三界合一 |\n| 五行 | 化禀性 | 孕妇拨阴取阳 |\n| 四大界 | 升志意 | 志界婚姻→最好后代 |\n| 性理疗病 | 认不是找好处 | 家庭病从夫妇不和来 |\n| **崇俭胎教** | **重立人根** | **从源头改命** |\n\n---\n\n**《王凤仪性命哲学浅述》五篇，到这里就读完了。**\n\n以志先生在东京1997年写后记：本书据王凤仪语录、朱循天《侍坐随笔》编成，愿与有缘人共勉。\n\n你若愿意，咱们可以：\n- 把五篇合成一张**日用修行总表**\n- 或挑一个你最关心的议题（婚姻、亲子、化性、劝病）**单独深讲、对照生活**\n\n哪一条你最有感触？\n\n[REDACTED]"
        }
      ]
    }
  ]
}